glai/__init__.py
glai/ai/__init__.py
glai/ai/auto_ai.py
glai/ai/easy_ai.py
glai/messages/__init__.py
glai/messages/messages.py
glai-0.1.3.dist-info/METADATA
glai-0.1.3.dist-info/WHEEL
glai-0.1.3.dist-info/top_level.txt
glai-0.1.3.dist-info/RECORD
