Metadata-Version: 2.1
Name: glai
Version: 0.1.3
Summary: Easy deployment of quantized llama models on cpu
Home-page: https://github.com/laelhalawani/glai
Author: Łael Al-Halawani
Author-email: laelhalawani@gmail.com
Keywords: llama,ai,artificial intelligence,natural language processing,nlp,quantization,cpu,deployment,inference,model,models,model database,model repo,model repository,model library,model libraries,gguf,llm cpu,llm
Classifier: Development Status :: 3 - Alpha
Classifier: Intended Audience :: Developers
Classifier: Intended Audience :: Education
Classifier: Intended Audience :: Information Technology
Classifier: License :: Free for non-commercial use
Classifier: Natural Language :: English
Classifier: Operating System :: OS Independent
Classifier: Programming Language :: C++
Classifier: Programming Language :: Python :: 3.1
Classifier: Topic :: Text Processing
Classifier: Topic :: Scientific/Engineering :: Artificial Intelligence
Requires-Dist: requests >=2.31.0
Requires-Dist: beautifulsoup4 >=4.9.3
Requires-Dist: gguf-llama >=0.0.18
Requires-Dist: gguf-modeldb >=0.0.3
